pydbantic/__init__.py
pydbantic/cache.py
pydbantic/core.py
pydbantic/database.py
pydbantic/translations.py
pydbantic-0.0.47.dist-info/LICENSE
pydbantic-0.0.47.dist-info/METADATA
pydbantic-0.0.47.dist-info/WHEEL
pydbantic-0.0.47.dist-info/top_level.txt
pydbantic-0.0.47.dist-info/RECORD
