Metadata-Version: 2.1
Name: pydbantic
Version: 0.0.47
Summary: 'db' within pydantic - A single model for shaping, creating, accessing, storing data within a Database
Home-page: https://github.com/codemation/pydbantic
Author: Joshua Jamison
Author-email: joshjamison1@gmail.com
License: UNKNOWN
Platform: UNKNOWN
Classifier: Programming Language :: Python :: 3
Classifier: License :: OSI Approved :: MIT License
Classifier: Operating System :: OS Independent
Classifier: Framework :: Pydantic
Classifier: Framework :: FastAPI
Classifier: Topic :: Database
Requires-Python: >=3.7, <4
Requires-Dist: SQLAlchemy ==1.4.49
Requires-Dist: databases ==0.8.0
Requires-Dist: redis >=4.2.0
Requires-Dist: pydantic >=1.9.1
Requires-Dist: pydantic <2
Requires-Dist: alembic ==1.8.1
Provides-Extra: all
Requires-Dist: SQLAlchemy ==1.4.49 ; extra == 'all'
Requires-Dist: databases ==0.8.0 ; extra == 'all'
Requires-Dist: redis >=4.2.0 ; extra == 'all'
Requires-Dist: pydantic >=1.9.1 ; extra == 'all'
Requires-Dist: pydantic <2 ; extra == 'all'
Requires-Dist: alembic ==1.8.1 ; extra == 'all'
Requires-Dist: asyncpg ==0.24.0 ; extra == 'all'
Requires-Dist: psycopg2 ==2.9.1 ; extra == 'all'
Requires-Dist: aiomysql ==0.0.21 ; extra == 'all'
Requires-Dist: cryptography ==3.4.8 ; extra == 'all'
Requires-Dist: mysqlclient ==2.0.3 ; extra == 'all'
Requires-Dist: PyMySQL ==0.9.3 ; extra == 'all'
Requires-Dist: aiosqlite ==0.17.0 ; extra == 'all'
Provides-Extra: mysql
Requires-Dist: aiomysql ==0.0.21 ; extra == 'mysql'
Requires-Dist: cryptography ==3.4.8 ; extra == 'mysql'
Requires-Dist: mysqlclient ==2.0.3 ; extra == 'mysql'
Requires-Dist: PyMySQL ==0.9.3 ; extra == 'mysql'
Provides-Extra: postgres
Requires-Dist: asyncpg ==0.24.0 ; extra == 'postgres'
Requires-Dist: psycopg2 ==2.9.1 ; extra == 'postgres'
Provides-Extra: sqlite
Requires-Dist: aiosqlite ==0.17.0 ; extra == 'sqlite'
